datapolish/__init__.py
datapolish/cleaner.py
datapolish/describer.py
datapolish/explainer.py
datapolish/visualizer.py
datapolish-1.0.0.dist-info/licenses/LICENSE
datapolish-1.0.0.dist-info/METADATA
datapolish-1.0.0.dist-info/WHEEL
datapolish-1.0.0.dist-info/top_level.txt
datapolish-1.0.0.dist-info/RECORD
