Metadata-Version: 2.4
Name: datapolish
Version: 1.0.0
Summary: AI-powered data cleaning library with intelligent recommendations and professional visualizations
Home-page: https://github.com/akinboye/datapolish
Author: Akinboye Yusuff
Author-email: Akinboye Yusuff <mailakinboye@gmail.com>
License: MIT
Project-URL: Homepage, https://github.com/akinboye/datapolish
Project-URL: Documentation, https://github.com/akinboye/datapolish#readme
Project-URL: Repository, https://github.com/akinboye/datapolish
Project-URL: Bug Tracker, https://github.com/akinboye/datapolish/issues
Keywords: data cleaning,data quality,data preprocessing,data science,machine learning,AI
Classifier: Development Status :: 5 - Production/Stable
Classifier: Intended Audience :: Developers
Classifier: Intended Audience :: Science/Research
Classifier: License :: OSI Approved :: MIT License
Classifier: Programming Language :: Python :: 3
Classifier: Programming Language :: Python :: 3.7
Classifier: Programming Language :: Python :: 3.8
Classifier: Programming Language :: Python :: 3.9
Classifier: Programming Language :: Python :: 3.10
Classifier: Programming Language :: Python :: 3.11
Classifier: Programming Language :: Python :: 3.12
Classifier: Topic :: Scientific/Engineering :: Information Analysis
Classifier: Topic :: Software Development :: Libraries :: Python Modules
Requires-Python: >=3.7
License-File: LICENSE
Requires-Dist: pandas>=1.3.0
Requires-Dist: numpy>=1.20.0
Requires-Dist: scipy>=1.7.0
Requires-Dist: matplotlib>=3.3.0
Requires-Dist: seaborn>=0.11.0
Requires-Dist: openpyxl>=3.0.0
Provides-Extra: dev
Requires-Dist: pytest>=6.0; extra == "dev"
Requires-Dist: pytest-cov>=2.0; extra == "dev"
Requires-Dist: black>=21.0; extra == "dev"
Requires-Dist: flake8>=3.9; extra == "dev"
Dynamic: author
Dynamic: home-page
Dynamic: license-file
Dynamic: requires-python
